app.py
config/__init__.py
config/config.properties
config/config.py
db/__init__.py
db/base_fuyao_db.py
db/fuyao_run_info_tbl.py
fuyao_debug_app-0.6.2.data/data/config/config.properties
fuyao_debug_app-0.6.2.data/data/db/config.properties
utils/__init__.py
utils/fuyao_log_ali.py
utils/sigs.py
utils/utils.py
fuyao_debug_app-0.6.2.dist-info/METADATA
fuyao_debug_app-0.6.2.dist-info/WHEEL
fuyao_debug_app-0.6.2.dist-info/entry_points.txt
fuyao_debug_app-0.6.2.dist-info/top_level.txt
fuyao_debug_app-0.6.2.dist-info/RECORD
