Metadata-Version: 2.1
Name: fuyao-debug-app
Version: 0.6.2
Requires-Dist: SQLAlchemy ==1.4.45
Requires-Dist: pymysql
